CHANGES.rst
CONTRIBUTORS.rst
MANIFEST.in
README.rst
setup.py
docs/LICENSE.GPL
docs/LICENSE.txt
src/interlegis/__init__.py
src/interlegis.portalmodelo.transparency.egg-info/PKG-INFO
src/interlegis.portalmodelo.transparency.egg-info/SOURCES.txt
src/interlegis.portalmodelo.transparency.egg-info/dependency_links.txt
src/interlegis.portalmodelo.transparency.egg-info/entry_points.txt
src/interlegis.portalmodelo.transparency.egg-info/namespace_packages.txt
src/interlegis.portalmodelo.transparency.egg-info/not-zip-safe
src/interlegis.portalmodelo.transparency.egg-info/requires.txt
src/interlegis.portalmodelo.transparency.egg-info/top_level.txt
src/interlegis/portalmodelo/__init__.py
src/interlegis/portalmodelo/transparency/__init__.py
src/interlegis/portalmodelo/transparency/config.py
src/interlegis/portalmodelo/transparency/configure.zcml
src/interlegis/portalmodelo/transparency/dependencies.zcml
src/interlegis/portalmodelo/transparency/interfaces.py
src/interlegis/portalmodelo/transparency/profiles.zcml
src/interlegis/portalmodelo/transparency/testing.py
src/interlegis/portalmodelo/transparency/browser/__init__.py
src/interlegis/portalmodelo/transparency/browser/configure.zcml
src/interlegis/portalmodelo/transparency/browser/downloads_view.py
src/interlegis/portalmodelo/transparency/browser/view.py
src/interlegis/portalmodelo/transparency/browser/templates/view.pt
src/interlegis/portalmodelo/transparency/content/__init__.py
src/interlegis/portalmodelo/transparency/content/csvdata.py
src/interlegis/portalmodelo/transparency/content/schema/CSVData.xml
src/interlegis/portalmodelo/transparency/content/schema/__init__.py
src/interlegis/portalmodelo/transparency/profiles/default/browserlayer.xml
src/interlegis/portalmodelo/transparency/profiles/default/metadata.xml
src/interlegis/portalmodelo/transparency/profiles/default/rolemap.xml
src/interlegis/portalmodelo/transparency/profiles/default/types.xml
src/interlegis/portalmodelo/transparency/profiles/default/types/CSVData.xml
src/interlegis/portalmodelo/transparency/profiles/uninstall/interlegis.portalmodelo.transparency.txt
src/interlegis/portalmodelo/transparency/static/csv_download.png
src/interlegis/portalmodelo/transparency/static/csv_icon.png
src/interlegis/portalmodelo/transparency/static/html_download.png
src/interlegis/portalmodelo/transparency/static/json_download.png
src/interlegis/portalmodelo/transparency/static/pdf_download.png
src/interlegis/portalmodelo/transparency/static/txt_download.png
