Metadata-Version: 1.1
Name: interlegis.portalmodelo.transparency
Version: 1.0rc5
Summary: Tipo de conteúdo do Portal Modelo para publicação de dados estruturados em formato CSV
Home-page: https://github.com/interlegis/interlegis.portalmodelo.transparency
Author: Programa Interlegis
Author-email: ti@interlegis.leg.br
License: GPLv2
Keywords: interlegis portalmodelo transparencia lrf
Platform: UNKNOWN
Classifier: Development Status :: 3 - Alpha
Classifier: Environment :: Web Environment
Classifier: Framework :: Plone
Classifier: Framework :: Plone :: 4.3
Classifier: Intended Audience :: System Administrators
Classifier: License :: OSI Approved :: GNU General Public License v2 (GPLv2)
Classifier: Operating System :: OS Independent
Classifier: Programming Language :: Python
Classifier: Programming Language :: Python :: 2.7
Classifier: Topic :: Software Development :: Libraries :: Python Modules
